zippity_py/__init__.py
zippity_py/cli.py
zippity_py/cli_utils.py
zippity_py/file_extensions.py
zippity_py/fs_utils.py
zippity_py/template/__init__.py
zippity_py/template/render.py
zippity_py/template/template.md.jinja
zippity_py/todo_utils.py
zippity_py-0.1.1.dist-info/METADATA
zippity_py-0.1.1.dist-info/WHEEL
zippity_py-0.1.1.dist-info/entry_points.txt
zippity_py-0.1.1.dist-info/RECORD
