Metadata-Version: 2.1
Name: zippity-py
Version: 0.1.1
Summary: dum lil CLI tool to create summary files with todos and extracts from source code for chatbots.
Author: lumpenspace
Author-email: lumpenspace@gmail.com
Requires-Python: >=3.8,<4.0
Classifier: Programming Language :: Python :: 3
Classifier: Programming Language :: Python :: 3.8
Classifier: Programming Language :: Python :: 3.9
Classifier: Programming Language :: Python :: 3.10
Classifier: Programming Language :: Python :: 3.11
Classifier: Programming Language :: Python :: 3.12
Requires-Dist: click (>=8.1.7,<9.0.0)
Requires-Dist: clipboard-maximizer (>=0.2.3,<0.3.0)
Requires-Dist: comment-parser (>=1.2.4,<2.0.0)
Requires-Dist: gitignore-parser (>=0.1.10,<0.2.0)
Requires-Dist: jinja2 (>=3.1.3,<4.0.0)
